CHANGES.rst
MANIFEST.in
README.rst
license.txt
setup.py
emspring.egg-info/PKG-INFO
emspring.egg-info/SOURCES.txt
emspring.egg-info/dependency_links.txt
emspring.egg-info/entry_points.txt
emspring.egg-info/not-zip-safe
emspring.egg-info/top_level.txt
spring/__init__.py
spring/csinfrastr/__init__.py
spring/csinfrastr/csdatabase.py
spring/csinfrastr/csdocu.py
spring/csinfrastr/csfeatures.py
spring/csinfrastr/csgui.py
spring/csinfrastr/cslaunch.py
spring/csinfrastr/cslogger.py
spring/csinfrastr/csproductivity.py
spring/csinfrastr/csreadinput.py
spring/images/spring2d_logo.png
spring/images/spring3d_logo.png
spring/images/springscan_logo.png
spring/images/icons/clipboard.png
spring/images/icons/exit.png
spring/images/icons/export_table.png
spring/images/icons/help.png
spring/images/icons/open.png
spring/images/icons/save.png
spring/micprgs/__init__.py
spring/micprgs/micctfdetermine.py
spring/micprgs/micctfdetermine_mpi.py
spring/micprgs/micexam.py
spring/micprgs/micexam_mpi.py
spring/micprgs/michelixtrace.py
spring/micprgs/michelixtrace_helperfunctions.py
spring/micprgs/michelixtrace_mpi.py
spring/micprgs/michelixtracegrid.py
spring/micprgs/scandotfit.py
spring/micprgs/scanlinefit.py
spring/micprgs/scanrowcolcorr.py
spring/micprgs/scansplit.py
spring/micprgs/scansplit_mpi.py
spring/particle2d/__init__.py
spring/particle2d/particlealign2d.py
spring/particle2d/particlealign2d_mpi.py
spring/particle2d/particleclass.py
spring/particle2d/particlestack.py
spring/segment2d/__init__.py
spring/segment2d/segclassexam.py
spring/segment2d/segclassexam_mpi.py
spring/segment2d/segclasslayer.py
spring/segment2d/seglayer2lattice.py
spring/segment2d/segment.py
spring/segment2d/segment_int.py
spring/segment2d/segment_mpi.py
spring/segment2d/segment_prep.py
spring/segment2d/segmentalign2d.py
spring/segment2d/segmentalign2d_mpi.py
spring/segment2d/segmentalign2d_prep.py
spring/segment2d/segmentclass.py
spring/segment2d/segmentctfapply.py
spring/segment2d/segmentctfapply_mpi.py
spring/segment2d/segmentexam.py
spring/segment2d/segmentexam_mpi.py
spring/segment2d/segmentkmeans.py
spring/segment2d/segmentkmeans_app.py
spring/segment2d/segmentplot.py
spring/segment2d/segmentselect.py
