Metadata-Version: 1.1
Name: emspring
Version: 0.87.1718
Summary: Electron Microscopy Single-Particle Based Helical Reconstruction
Home-page: http://spring.fz-juelich.de
Author: Carsten Sachse
Author-email: carsten.sachse@gmail.com
License: Modified BSD License
Keywords: Electron cryomicroscopy,cryo-EM,image processing,SPARX,EMAN2,Helical assembly,3D reconstruction,helical symmetry
Platform: UNKNOWN
Classifier: Development Status :: 5 - Production/Stable
Classifier: Operating System :: Unix
Classifier: Environment :: X11 Applications :: Qt
Classifier: Intended Audience :: Science/Research
Classifier: License :: OSI Approved :: BSD License
Classifier: Programming Language :: Python
Classifier: Topic :: Scientific/Engineering :: Image Recognition
